{"forms":{"default":{"identifier":"","isMega":"0","isDefault":"1","stats":{"hp":"45","atk":"55","def":"39","spAtk":"35","spDef":"39","speed":"42"},"types":["Normal"],"efficiency":{"0":["Ghost"],"25":[],"50":[],"100":["Normal","Flying","Poison","Ground","Rock","Bug","Steel","Fire","Water","Grass","Electric","Psychic","Ice","Dragon","Dark","Fairy"],"200":["Fighting"],"400":[]},"abilities":[{"isHidden":"0","translations":{"ja-Hrkt":{"id":1,"language":"ja-Hrkt","name":"にげあし","description":"やせいの　ポケモンから\nかならず　にげられる。"},"ko":{"id":3,"language":"ko","name":"도주","description":"야생 포켓몬으로부터\n반드시 도망칠 수 있다."},"zh-Hant":{"id":4,"language":"zh-Hant","name":"逃跑","description":"一定能從野生寶可夢\n那裡逃走。"},"fr":{"id":5,"language":"fr","name":"Fuite","description":"Permet de fuir n’importe quel Pokémon sauvage."},"de":{"id":6,"language":"de","name":"Angsthase","description":"Die Flucht vor wilden Pokémon gelingt immer."},"es":{"id":7,"language":"es","name":"Fuga","description":"Permite escapar de todos los Pokémon salvajes."},"it":{"id":8,"language":"it","name":"Fugafacile","description":"Garantisce la fuga dai Pokémon selvatici."},"en":{"id":9,"language":"en","name":"Run Away","description":"Enables a sure getaway from wild Pokémon."},"ja":{"id":11,"language":"ja","name":"にげあし","description":"野生の　ポケモンから\n必ず　逃げられる。"},"zh-Hans":{"id":12,"language":"zh-Hans","name":"逃跑","description":"一定能从野生宝可梦\n那儿逃走。"}},"id":"50"},{"isHidden":"0","translations":{"ja-Hrkt":{"id":1,"language":"ja-Hrkt","name":"するどいめ","description":"するどい　めの　おかげで\nめいちゅうりつを　さげられない。"},"ko":{"id":3,"language":"ko","name":"날카로운눈","description":"날카로운 눈 덕분에\n명중률이 떨어지지 않는다."},"zh-Hant":{"id":4,"language":"zh-Hant","name":"銳利目光","description":"靠著銳利的目光，\n命中率不會被降低。"},"fr":{"id":5,"language":"fr","name":"Regard Vif","description":"Les yeux perçants du Pokémon empêchent\nsa Précision de baisser."},"de":{"id":6,"language":"de","name":"Adlerauge","description":"Sein scharfer Blick hindert Angreifer daran,\nseine Genauigkeit zu senken."},"es":{"id":7,"language":"es","name":"Vista Lince","description":"La aguda vista de este Pokémon evita que disminuya\nsu Precisión."},"it":{"id":8,"language":"it","name":"Sguardofermo","description":"La vista acuta del Pokémon impedisce che la sua\nprecisione diminuisca."},"en":{"id":9,"language":"en","name":"Keen Eye","description":"Keen eyes prevent other Pokémon from lowering this\nPokémon’s accuracy."},"ja":{"id":11,"language":"ja","name":"するどいめ","description":"鋭い　目の　おかげで\n命中率を　下げられない。"},"zh-Hans":{"id":12,"language":"zh-Hans","name":"锐利目光","description":"多亏了锐利的目光，\n命中率不会被降低。"}},"id":"51"},{"isHidden":"1","translations":{"ja-Hrkt":{"id":1,"language":"ja-Hrkt","name":"アナライズ","description":"いちばん　さいごに　わざを　だすと\nわざの　いりょくが　あがる。"},"ko":{"id":3,"language":"ko","name":"애널라이즈","description":"제일 마지막에 기술을 쓰면\n기술의 위력이 올라간다."},"zh-Hant":{"id":4,"language":"zh-Hant","name":"分析","description":"如果在最後使出招式，\n招式就會變強。"},"fr":{"id":5,"language":"fr","name":"Analyste","description":"Augmente la puissance des capacités du Pokémon\ns’il attaque en dernier."},"de":{"id":6,"language":"de","name":"Analyse","description":"Greift das Pokémon zuletzt an, erhöht sich die\nStärke der Attacke, die es einsetzt."},"es":{"id":7,"language":"es","name":"Cálculo Final","description":"Aumenta la potencia del movimiento si es el último en\natacar."},"it":{"id":8,"language":"it","name":"Ponderazione","description":"Se il Pokémon agisce per ultimo, la potenza\ndella mossa aumenta."},"en":{"id":9,"language":"en","name":"Analytic","description":"Boosts move power when the Pokémon moves last."},"ja":{"id":11,"language":"ja","name":"アナライズ","description":"いちばん　最後に　技を　出すと\n技の　威力が　上がる。"},"zh-Hans":{"id":12,"language":"zh-Hans","name":"分析","description":"如果在最后使出招式，\n招式的威力会提高。"}},"id":"148"}]}}}