{"forms":{"default":{"identifier":"","isMega":"0","isDefault":"1","stats":{"hp":"38","atk":"35","def":"40","spAtk":"27","spDef":"25","speed":"35"},"types":["Bug"],"efficiency":{"0":[],"25":[],"50":["Fighting","Ground","Grass"],"100":["Normal","Poison","Bug","Ghost","Steel","Water","Electric","Psychic","Ice","Dragon","Dark","Fairy"],"200":["Flying","Rock","Fire"],"400":[]},"abilities":[{"isHidden":"0","translations":{"ja-Hrkt":{"id":1,"language":"ja-Hrkt","name":"りんぷん","description":"りんぷんに　まもられて\nわざの　ついかこうかを　うけなくなる。"},"ko":{"id":3,"language":"ko","name":"인분","description":"인분에 보호받아\n기술의 추가 효과를 받지 않게 된다."},"zh-Hant":{"id":4,"language":"zh-Hant","name":"鱗粉","description":"被鱗粉守護著，\n不會受到招式的追加效果影響。"},"fr":{"id":5,"language":"fr","name":"Écran Poudre","description":"Le Pokémon dispose d’un écran naturel qui le\nprotège des effets additionnels des attaques\nennemies."},"de":{"id":6,"language":"de","name":"Puderabwehr","description":"Blockiert durch Puder die Zusatzeffekte\ngegnerischer Angriffe."},"es":{"id":7,"language":"es","name":"Polvo Escudo","description":"El polvo de escamas que lo envuelve lo protege de\nlos efectos secundarios de los ataques recibidos."},"it":{"id":8,"language":"it","name":"Polvoscudo","description":"Il Pokémon è protetto da uno strato di scaglie\nche annulla gli effetti secondari delle mosse subite."},"en":{"id":9,"language":"en","name":"Shield Dust","description":"This Pokémon’s dust blocks the additional effects of\nattacks taken."},"ja":{"id":11,"language":"ja","name":"りんぷん","description":"りんぷんに　守られて\n技の　追加効果を　受けなくなる。"},"zh-Hans":{"id":12,"language":"zh-Hans","name":"鳞粉","description":"被鳞粉守护着，\n不会受到招式的追加效果影响。"}},"id":"19"},{"isHidden":"0","translations":{"ja-Hrkt":{"id":1,"language":"ja-Hrkt","name":"ふくがん","description":"ふくがんを　もっているため\nわざの　めいちゅうりつが　あがる。"},"ko":{"id":3,"language":"ko","name":"복안","description":"복안을 가지고 있어\n기술의 명중률이 올라간다."},"zh-Hant":{"id":4,"language":"zh-Hant","name":"複眼","description":"因為擁有複眼，\n會提高招式的命中率。"},"fr":{"id":5,"language":"fr","name":"Œil Composé","description":"Les yeux à facettes du Pokémon augmentent\nsa Précision."},"de":{"id":6,"language":"de","name":"Facettenauge","description":"Erhöht die Genauigkeit von Attacken."},"es":{"id":7,"language":"es","name":"Ojo Compuesto","description":"Aumenta la precisión de sus movimientos."},"it":{"id":8,"language":"it","name":"Insettocchi","description":"La precisione del Pokémon aumenta grazie ai suoi\nocchi composti."},"en":{"id":9,"language":"en","name":"Compound Eyes","description":"The Pokémon’s compound eyes boost its accuracy."},"ja":{"id":11,"language":"ja","name":"ふくがん","description":"複眼を　持っているため\n技の　命中率が　上がる。"},"zh-Hans":{"id":12,"language":"zh-Hans","name":"复眼","description":"因为拥有复眼，\n招式的命中率会提高。"}},"id":"14"},{"isHidden":"1","translations":{"ja-Hrkt":{"id":1,"language":"ja-Hrkt","name":"フレンドガード","description":"みかたの　ダメージを\nへらすことが　できる。"},"ko":{"id":3,"language":"ko","name":"프렌드가드","description":"같은 편의 데미지를\n줄일 수 있다."},"zh-Hant":{"id":4,"language":"zh-Hant","name":"友情防守","description":"可以減少我方受到的傷害。"},"fr":{"id":5,"language":"fr","name":"Garde Amie","description":"Diminue les dégâts subis par les alliés."},"de":{"id":6,"language":"de","name":"Freundeshut","description":"Kann den Schaden, den Mitstreiter erleiden,\nverringern."},"es":{"id":7,"language":"es","name":"Compiescolta","description":"Reduce el daño que sufren los aliados."},"it":{"id":8,"language":"it","name":"Amicoscudo","description":"I danni inflitti agli alleati del Pokémon\nvengono ridotti."},"en":{"id":9,"language":"en","name":"Friend Guard","description":"Reduces damage done to allies."},"ja":{"id":11,"language":"ja","name":"フレンドガード","description":"味方の　ダメージを\n減らすことが　できる。"},"zh-Hans":{"id":12,"language":"zh-Hans","name":"友情防守","description":"可以减少我方的伤害。"}},"id":"132"}]}}}