{"forms":{"default":{"identifier":"","isMega":"0","isDefault":"1","stats":{"hp":"71","atk":"137","def":"37","spAtk":"137","spDef":"37","speed":"151"},"types":["Bug","Fighting"],"efficiency":{"0":[],"25":[],"50":["Fighting","Ground","Bug","Grass","Dark"],"100":["Normal","Poison","Rock","Ghost","Steel","Water","Electric","Ice","Dragon"],"200":["Fire","Psychic","Fairy"],"400":["Flying"]},"abilities":[{"isHidden":"0","translations":{"ja-Hrkt":{"id":1,"language":"ja-Hrkt","name":"ビーストブースト","description":"あいてを　たおしたとき\nじぶんの　いちばん　たかい\nのうりょくが　あがる。"},"ko":{"id":3,"language":"ko","name":"비스트부스트","description":"상대를 기절시켰을 때\n자신의 가장 높은\n능력이 올라간다."},"zh-Hant":{"id":4,"language":"zh-Hant","name":"異獸提升","description":"打倒對手的時候，\n會提高自己最高的那項能力。"},"fr":{"id":5,"language":"fr","name":"Boost Chimère","description":"Augmente la stat la plus élevée du Pokémon\ns’il met K.O. un autre Pokémon pendant son tour."},"de":{"id":6,"language":"de","name":"Bestien-Boost","description":"Erhöht in jeder Runde, in der es ein anderes\nPokémon besiegt, seinen höchsten Statuswert."},"es":{"id":7,"language":"es","name":"Ultraimpulso","description":"Si el Pokémon derrota a un rival en ese turno,\naumenta su característica más fuerte."},"it":{"id":8,"language":"it","name":"Ultraboost","description":"Se il Pokémon ha mandato KO almeno un altro\nPokémon nel turno, aumenta la propria statistica\ndi punta."},"en":{"id":9,"language":"en","name":"Beast Boost","description":"The Pokémon boosts its most proficient stat each\ntime it knocks out a Pokémon."},"ja":{"id":11,"language":"ja","name":"ビーストブースト","description":"相手を　倒したとき\n自分の　いちばん　高い\n能力が　上がる。"},"zh-Hans":{"id":12,"language":"zh-Hans","name":"异兽提升","description":"打倒对手的时候，\n自己最高的那项能力会提高。"}},"id":"224"}]}}}