{"forms":{"default":{"identifier":"","isMega":"0","isDefault":"1","stats":{"hp":"60","atk":"65","def":"60","spAtk":"130","spDef":"75","speed":"110"},"types":["Ghost","Poison"],"efficiency":{"0":["Normal","Fighting"],"25":["Poison","Bug"],"50":["Grass","Fairy"],"100":["Flying","Rock","Steel","Fire","Water","Electric","Ice","Dragon"],"200":["Ground","Ghost","Psychic","Dark"],"400":[]},"abilities":[{"isHidden":"0","translations":{"ja-Hrkt":{"id":1,"language":"ja-Hrkt","name":"のろわれボディ","description":"こうげきを　うけると　あいての　わざを\nかなしばり　じょうたいに\nすることが　ある。"},"ko":{"id":3,"language":"ko","name":"저주받은바디","description":"공격을 받으면 상대의 기술을\n사슬묶기 상태로\n만들 때가 있다."},"zh-Hant":{"id":4,"language":"zh-Hant","name":"詛咒之軀","description":"受到攻擊時，\n有時會把對手的招式\n變為定身法狀態。"},"fr":{"id":5,"language":"fr","name":"Corps Maudit","description":"Quand le Pokémon est touché par une capacité,\nil inflige parfois Entrave sur celle-ci."},"de":{"id":6,"language":"de","name":"Tastfluch","description":"Blockiert eventuell die Attacke, mit welcher der\nAngreifer es getroffen hat."},"es":{"id":7,"language":"es","name":"Cuerpo Maldito","description":"Puede anular el movimiento usado en su contra."},"it":{"id":8,"language":"it","name":"Corpofunesto","description":"A volte blocca l’ultima mossa usata dal nemico."},"en":{"id":9,"language":"en","name":"Cursed Body","description":"May disable a move used on the Pokémon."},"ja":{"id":11,"language":"ja","name":"のろわれボディ","description":"攻撃を　受けると　相手の　技を\nかなしばり状態に\nすることが　ある。"},"zh-Hans":{"id":12,"language":"zh-Hans","name":"诅咒之躯","description":"受到攻击时，\n有时会把对手的招式\n变为定身法状态。"}},"id":"130"}]},"mega":{"identifier":"mega","isMega":"1","isDefault":"0","stats":{"hp":"60","atk":"65","def":"80","spAtk":"170","spDef":"95","speed":"130"},"types":["Ghost","Poison"],"efficiency":{"0":["Normal","Fighting"],"25":["Poison","Bug"],"50":["Grass","Fairy"],"100":["Flying","Rock","Steel","Fire","Water","Electric","Ice","Dragon"],"200":["Ground","Ghost","Psychic","Dark"],"400":[]},"abilities":[{"isHidden":"0","translations":{"ja-Hrkt":{"id":1,"language":"ja-Hrkt","name":"かげふみ","description":"あいての　かげを　ふみ\nにげたり　こうたい　できなくする。"},"ko":{"id":3,"language":"ko","name":"그림자밟기","description":"상대의 그림자를 밟아\n도망치거나 교체할 수 없게 한다."},"zh-Hant":{"id":4,"language":"zh-Hant","name":"踩影","description":"踩住對手的影子\n使其無法逃走或替換。"},"fr":{"id":5,"language":"fr","name":"Marque Ombre","description":"Empêche le Pokémon ennemi de quitter le combat."},"de":{"id":6,"language":"de","name":"Wegsperre","description":"Hindert den Gegner an der Flucht beziehungsweise\nam Auswechseln, indem es ihm den Weg versperrt."},"es":{"id":7,"language":"es","name":"Sombra Trampa","description":"Evita que el enemigo huya o sea cambiado por otro."},"it":{"id":8,"language":"it","name":"Pedinombra","description":"Calpesta l’ombra del nemico impedendogli la fuga\no la sostituzione."},"en":{"id":9,"language":"en","name":"Shadow Tag","description":"This Pokémon steps on the opposing Pokémon’s\nshadow to prevent it from escaping."},"ja":{"id":11,"language":"ja","name":"かげふみ","description":"相手の　影を　踏み\n逃げたり　交代　できなくする。"},"zh-Hans":{"id":12,"language":"zh-Hans","name":"踩影","description":"踩住对手的影子\n使其无法逃走或替换。"}},"id":"23"}]}}}